[
	{
		"Task": "New task 3",
		"Done": true,
		"CreateAt": "2022-02-04T00:13:04.581311-08:00",
		"CompleteAt": "2022-02-04T00:19:47.177665-08:00"
	},
	{
		"Task": "New task 1",
		"Done": false,
		"CreateAt": "2022-02-04T00:22:10.405689-08:00",
		"CompleteAt": "0001-01-01T00:00:00Z"
	},
	{
		"Task": "New task 2",
		"Done": false,
		"CreateAt": "2022-02-04T00:22:14.307359-08:00",
		"CompleteAt": "0001-01-01T00:00:00Z"
	},
	{
		"Task": "New task 3",
		"Done": false,
		"CreateAt": "2022-02-04T00:22:16.373599-08:00",
		"CompleteAt": "0001-01-01T00:00:00Z"
	},
	{
		"Task": "New task 4",
		"Done": false,
		"CreateAt": "2022-02-04T00:22:18.236503-08:00",
		"CompleteAt": "0001-01-01T00:00:00Z"
	},
	{
		"Task": "New task 5",
		"Done": false,
		"CreateAt": "2022-02-04T00:22:20.234479-08:00",
		"CompleteAt": "0001-01-01T00:00:00Z"
	},
	{
		"Task": "New task 6",
		"Done": false,
		"CreateAt": "2022-02-04T00:22:22.148972-08:00",
		"CompleteAt": "0001-01-01T00:00:00Z"
	}
]